canviewer/__init__.py
canviewer/_console.py
canviewer/_entrypoints.py
canviewer/_jsonify.py
canviewer/_monitor.py
canviewer/_utils.py
canviewer/py.typed
canviewer-1.5.0.dist-info/METADATA
canviewer-1.5.0.dist-info/WHEEL
canviewer-1.5.0.dist-info/entry_points.txt
canviewer-1.5.0.dist-info/RECORD
