Metadata-Version: 2.4
Name: canviewer
Version: 1.5.0
Summary: A CLI tool providing rich monitoring of CAN data
Project-URL: Documentation, https://github.com/Hedwyn/python-canviewer#readme
Project-URL: Issues, https://github.com/Hedwyn/python-canviewer/issues
Project-URL: Source, https://github.com/Hedwyn/python-canviewer
Author-email: Hedwyn <bpestourie@gmail.com>
License-Expression: MIT
Classifier: Development Status :: 4 - Beta
Classifier: Programming Language :: Python
Classifier: Programming Language :: Python :: 3.12
Classifier: Programming Language :: Python :: 3.13
Classifier: Programming Language :: Python :: Implementation :: CPython
Classifier: Programming Language :: Python :: Implementation :: PyPy
Requires-Python: >=3.12
Requires-Dist: asciichartpy
Requires-Dist: cantools
Requires-Dist: click
Requires-Dist: exhausterr~=0.2.0
Requires-Dist: inotify
Requires-Dist: pyperclip
Requires-Dist: python-can
Requires-Dist: rich
